cf_scraping/__init__.py
cf_scraping/interaction_views.py
cf_scraping/library.py
cf_scraping/version.py
cf_scraping/views.py
cf_scraping/visualization_views.py
cf_scraping/package_data/categories/a23d74eb-0c33-4adb-b37b-44a2a39084b5.json
cf_scraping/package_data/widgets/138a478c-d030-4d5e-b66c-0ca57d073777.json
cf_scraping/package_data/widgets/e6f70116-bca3-43f5-8a5c-25a700e3d457.json
cf_scraping/package_data/widgets/e99cc272-7943-4daf-8219-f3b7455050b3.json
cf_scraping-1.0.1.dist-info/LICENSE
cf_scraping-1.0.1.dist-info/METADATA
cf_scraping-1.0.1.dist-info/WHEEL
cf_scraping-1.0.1.dist-info/top_level.txt
cf_scraping-1.0.1.dist-info/RECORD
