Metadata-Version: 2.1
Name: cf-scraping
Version: 1.0.1
Summary: Web Scraping for ClowdFlows
Home-page: https://github.com/xflows/cf_scraping
Author: Janez Kranjc
Author-email: janez.kranjc@ijs.si
License: MIT License
Platform: UNKNOWN
Requires-Dist: requests
Requires-Dist: goose3
